mlc/.python-version
mlc/__init__.py
mlc/classifier/batch_classifier.py
mlc/constraints/__init__.py
mlc/constraints/backend.py
mlc/constraints/constraints.py
mlc/constraints/constraints_backend_executor.py
mlc/constraints/constraints_checker.py
mlc/constraints/constraints_executor.py
mlc/constraints/constraints_fixer.py
mlc/constraints/constraints_parser.py
mlc/constraints/numpy_backend.py
mlc/constraints/pytorch_backend.py
mlc/constraints/relation_constraint.py
mlc/constraints/utils.py
mlc/dataloaders/__init__.py
mlc/dataloaders/adversarial/__init__.py
mlc/dataloaders/adversarial/madry.py
mlc/dataloaders/dataloader.py
mlc/dataloaders/default.py
mlc/dataloaders/distribution/__init__.py
mlc/dataloaders/distribution/copula.py
mlc/dataloaders/distribution/smote.py
mlc/dataloaders/fast_dataloader.py
mlc/dataloaders/generative/__init__.py
mlc/dataloaders/generative/ctgan.py
mlc/dataloaders/generative/ddpm.py
mlc/dataloaders/generative/tab_ddpm/__init__.py
mlc/dataloaders/generative/tab_ddpm/gaussian_multinomial_diffusion.py
mlc/dataloaders/generative/tab_ddpm/lib/__init__.py
mlc/dataloaders/generative/tab_ddpm/lib/data.py
mlc/dataloaders/generative/tab_ddpm/lib/deep.py
mlc/dataloaders/generative/tab_ddpm/lib/env.py
mlc/dataloaders/generative/tab_ddpm/lib/metrics.py
mlc/dataloaders/generative/tab_ddpm/lib/util.py
mlc/dataloaders/generative/tab_ddpm/modules.py
mlc/dataloaders/generative/tab_ddpm/sample.py
mlc/dataloaders/generative/tab_ddpm/train.py
mlc/dataloaders/generative/tab_ddpm/utils.py
mlc/dataloaders/generative/tab_ddpm/utils_train.py
mlc/dataloaders/generative/tvae.py
mlc/dataloaders/sdv.py
mlc/dataloaders/semisup.py
mlc/datasets/dataset.py
mlc/datasets/dataset_factory.py
mlc/datasets/processing.py
mlc/datasets/samples/__init__.py
mlc/datasets/samples/airlines.py
mlc/datasets/samples/ctu_13_neris.py
mlc/datasets/samples/electricity.py
mlc/datasets/samples/lcld.py
mlc/datasets/samples/malware.py
mlc/datasets/samples/url.py
mlc/datasets/samples/wids.py
serval_ml_commons-0.1.5.dist-info/LICENSE
serval_ml_commons-0.1.5.dist-info/METADATA
serval_ml_commons-0.1.5.dist-info/WHEEL
serval_ml_commons-0.1.5.dist-info/RECORD
